{"cameraMode":{"drawMode":0,"name":"Shaded","section":"Shading Mode"},"sceneLighting":true,"audioPlay":false,"sceneViewState":{"showFog":true,"showMaterialUpdate":false,"showSkybox":true,"showFlares":true,"showImageEffects":true,"showParticleSystems":true,"showVisualEffectGraphs":true,"m_FxEnabled":true},"in2DMode":false,"pivot":{"x":2.7800536155700685,"y":1.7973014116287232,"z":7.595277786254883},"rotation":{"x":-0.11467167735099793,"y":-0.2319948971271515,"z":0.027551524341106416,"w":-0.9655471444129944},"size":8.957437515258789,"orthographic":false}